infi.recipe.python-0.6.25-py3.7-nspkg.pth
infi/recipe/python/__init__.py
infi/recipe/python/__version__.py
infi/recipe/python/download/__init__.py
infi/recipe/python/pack/__init__.py
infi/recipe/python/tests/__init__.py
infi.recipe.python-0.6.25.dist-info/LICENSE
infi.recipe.python-0.6.25.dist-info/METADATA
infi.recipe.python-0.6.25.dist-info/WHEEL
infi.recipe.python-0.6.25.dist-info/entry_points.txt
infi.recipe.python-0.6.25.dist-info/namespace_packages.txt
infi.recipe.python-0.6.25.dist-info/top_level.txt
infi.recipe.python-0.6.25.dist-info/RECORD
