Metadata-Version: 2.1
Name: infi.recipe.python
Version: 0.6.25
Summary: a recipe for downloading and packing portable builds of Python
Home-page: https://github.com/Infinidat/infi.recipe.python
Author: Arnon Yaari
Author-email: arnony@infinidat.com
License: BSD
Platform: UNKNOWN
Classifier: Intended Audience :: Developers
Classifier: Intended Audience :: System Administrators
Classifier: License :: OSI Approved :: BSD License
Classifier: Operating System :: OS Independent
Classifier: Programming Language :: Python
Classifier: Programming Language :: Python :: 2
Classifier: Programming Language :: Python :: 3
Classifier: Topic :: Software Development :: Libraries :: Python Modules
Requires-Dist: infi.os-info
Requires-Dist: setuptools
Requires-Dist: zc.buildout
